lowder/__init__.py
lowder-0.7.0.dist-info/LICENSE
lowder-0.7.0.dist-info/WHEEL
lowder-0.7.0.dist-info/METADATA
lowder-0.7.0.dist-info/RECORD
